<annotation>
	<folder>chief_2</folder>
	<filename>chief_099.jpg</filename>
	<path>C:\Users\arjun.ARJUNSINGH-SB2-\Pictures\HALO\chief_2\chief_099.jpg</path>
	<source>
		<database>Unknown</database>
	</source>
	<size>
		<width>240</width>
		<height>320</height>
		<depth>3</depth>
	</size>
	<segmented>0</segmented>
	<object>
		<name>spartan</name>
		<pose>Unspecified</pose>
		<truncated>0</truncated>
		<difficult>0</difficult>
		<bndbox>
			<xmin>42</xmin>
			<ymin>113</ymin>
			<xmax>166</xmax>
			<ymax>304</ymax>
		</bndbox>
	</object>
	<object>
		<name>pistol</name>
		<pose>Unspecified</pose>
		<truncated>0</truncated>
		<difficult>0</difficult>
		<bndbox>
			<xmin>43</xmin>
			<ymin>93</ymin>
			<xmax>76</xmax>
			<ymax>138</ymax>
		</bndbox>
	</object>
	<object>
		<name>up</name>
		<pose>Unspecified</pose>
		<truncated>0</truncated>
		<difficult>0</difficult>
		<bndbox>
			<xmin>42</xmin>
			<ymin>114</ymin>
			<xmax>164</xmax>
			<ymax>212</ymax>
		</bndbox>
	</object>
	<object>
		<name>chief</name>
		<pose>Unspecified</pose>
		<truncated>0</truncated>
		<difficult>0</difficult>
		<bndbox>
			<xmin>40</xmin>
			<ymin>111</ymin>
			<xmax>164</xmax>
			<ymax>302</ymax>
		</bndbox>
	</object>
</annotation>
